nerdvision/BreakpointService.py
nerdvision/ClientRegistration.py
nerdvision/ContextUploadService.py
nerdvision/FrameProcessor.py
nerdvision/GRPCService.py
nerdvision/NerdVision.py
nerdvision/Utils.py
nerdvision/__init__.py
nerdvision/__main__.py
nerdvision/models/EventSnapshot.py
nerdvision/models/__init__.py
nerdvision/settings/__init__.py
nerd_vision-0.0.4.dist-info/METADATA
nerd_vision-0.0.4.dist-info/WHEEL
nerd_vision-0.0.4.dist-info/namespace_packages.txt
nerd_vision-0.0.4.dist-info/top_level.txt
nerd_vision-0.0.4.dist-info/zip-safe
nerd_vision-0.0.4.dist-info/RECORD
